Lab 1/Full Adder/full_adder_gate.v
module full_adder_gate (a , b , c_in , s , c_out) ;
	input a, b, c_in ;
	output s, c_out ;
	
	wire sw1 , c_and1 , c_and2 , c_and3 , c_or1 ;
	
	xor (sw1 , a , b) ;
	xor (s , sw1 , c_in) ;
	
	and (c_and1 , a , b) ;
	and (c_and2 , a , c_in) ;
	and (c_and3 , b , c_in) ;
	or (c_or1 , c_and1 , c_and2) ;
	or (c_out , c_or1 , c_and3) ;
endmodule

module testbench ;
	reg a , b , c_in ;
	wire s , c_out ;
	full_adder_gate fa (a , b , c_in , s , c_out) ;

	
	initial
		begin
			$monitor ( , $time , " %b %b %b | %b %b " , a , b , c_in , s , c_out) ;
			$dumpfile ("adder.vcd") ;
			$dumpvars (0, testbench) ;
			#1 c_in = 1'b0 ; a = 1'b0 ; b = 1'b0 ;
			#1 b = 1'b1 ;
			#1 a = 1'b1 ; b = 1'b0 ;
			#1 b = 1'b1 ;
			#1 c_in = 1'b1 ; a = 1'b0 ; b = 1'b0 ;
			#1 b = 1'b1 ;
			#1 a = 1'b1 ; b = 1'b0 ;
			#1 b = 1'b1 ; 
			$finish ;
		end

endmodule

Lab 1/Full Adder/adder.vcd
$date
	Thu Jan 16 00:31:33 2020
$end
$version
	Icarus Verilog
$end
$timescale
	1s
$end
$scope module testbench $end
$var wire 1 ! s $end
$var wire 1 " c_out $end
$var reg 1 # a $end
$var reg 1 $ b $end
$var reg 1 % c_in $end
$scope module fa $end
$var wire 1 # a $end
$var wire 1 $ b $end
$var wire 1 & c_and1 $end
$var wire 1 ' c_and2 $end
$var wire 1 ( c_and3 $end
$var wire 1 % c_in $end
$var wire 1 ) c_or1 $end
$var wire 1 " c_out $end
$var wire 1 ! s $end
$var wire 1 * sw1 $end
$upscope $end
$upscope $end
$enddefinitions $end
#0
$dumpvars
x*
x)
x(
x'
x&
x%
x$
x#
x"
x!
$end
#1
0"
0!
0)
0*
0&
0'
0(
0$
0#
0%
#2
1!
1*
1$
#3
0$
1#
#4
1"
0!
1)
0*
1&
1$
#5
0"
0)
0&
1!
0$
0#
1%
#6
0!
1"
1*
1(
1$
#7
1)
0(
1'
0$
1#
#8
1!
0*
1&
1(
1$
