Lab 3/JK_ASYNC/jk_async.v
module jk_async (j, k, clearb, clk, q) ;
	input j, k, clearb, clk ;
	output q ;
	reg q ;
	
	always @(posedge clk or negedge clearb)
	begin
		if (!clearb) 
			q <= 1'b0 ;
		else 
			if (j == 1'b0 && k == 1'b0) 
				q <= q ;
			else if (j == 1'b0 && k == 1'b1) 
				q <= 1'b0 ;
			else if (j == 1'b1 && k == 1'b0) 
				q <= 1'b1 ;
			else if (j == 1'b1 && k == 1'b1) 
				q <= ~q ;
	end
endmodule

Lab 3/FOUR_BIT_COUNTER/four_bit_counter.v
``include"..\JK_ASYNC\jk_async.v"

module four_bit_counter (q3, q2, q1, q0, r3, r2, r1, r0, clk) ;
	input clk, r3, r2, r1, r0 ;
	output q3, q2, q1, q0 ;
	wire jk2, jk3 ;

	
	jk_async j0 (1'b1, 1'b1, r0, clk, q0) ;
	jk_async j1 (q0, q0, r1, clk, q1) ;
	and (jk2, q0, q1) ;
	
	jk_async j2 (jk2, jk2, r2, clk, q2) ;
	
	and (jk3, q2, jk2) ;
	jk_async j3 (jk3, jk3, r3, clk, q3) ;	
endmodule

// jk_async (j, k, clearb, clk, q) ;

Lab 3/FOUR_BIT_COUNTER/four_bit_counter_tb.v
`include "four_bit_counter.v"

module testbench ;
	reg r3, r2, r1, r0, clk ;
	wire q3, q2, q1, q0 ;
	
	four_bit_counter fbc (q3, q2, q1, q0, r3, r2, r1, r0, clk) ;
	
	always #5 clk = ~clk ;
	
	initial begin
		clk = 0 ;
		r3 = 0 ; r2 = 0 ; r1 = 0 ; r0 = 0 ;
		
		$monitor ("q3 = %b, q2 = %b, q1 = %b, q0 = %b\n", q3, q2, q1, q0) ;
		$dumpfile ("four_bit_counter.vcd") ;
		$dumpvars (0, testbench) ;
		
		#5 r3 = 1 ; r2 = 1 ; r1 = 1 ; r0 = 1 ;
		#10 ;
		#10 ;
		#10 ;
		#10 ;
		#10 ;
		#10 ;
		#10 ;
		#10 ;
		#10 ;
		#10 ;
		#10 ;
		#10 ;
		#10 ;
		#10 ;
		#10 $finish ;

	end
endmodule

Lab 3/FOUR_BIT_COUNTER/four_bit_counter.vcd
$date
	Mon Oct 28 15:37:51 2019
$end
$version
	Icarus Verilog
$end
$timescale
	1s
$end
$scope module testbench $end
$var wire 1 ! q3 $end
$var wire 1 " q2 $end
$var wire 1 # q1 $end
$var wire 1 $ q0 $end
$var reg 1 % clk $end
$var reg 1 & r0 $end
$var reg 1 ' r1 $end
$var reg 1 ( r2 $end
$var reg 1 ) r3 $end
$scope module fbc $end
$var wire 1 % clk $end
$var wire 1 * jk2 $end
$var wire 1 + jk3 $end
$var wire 1 & r0 $end
$var wire 1 ' r1 $end
$var wire 1 ( r2 $end
$var wire 1 ) r3 $end
$var wire 1 ! q3 $end
$var wire 1 " q2 $end
$var wire 1 # q1 $end
$var wire 1 $ q0 $end
$scope module j0 $end
$var wire 1 & clearb $end
$var wire 1 % clk $end
$var wire 1 , j $end
$var wire 1 - k $end
$var reg 1 $ q $end
$upscope $end
$scope module j1 $end
$var wire 1 ' clearb $end
$var wire 1 % clk $end
$var wire 1 $ j $end
$var wire 1 $ k $end
$var reg 1 # q $end
$upscope $end
$scope module j2 $end
$var wire 1 ( clearb $end
$var wire 1 % clk $end
$var wire 1 * j $end
$var wire 1 * k $end
$var reg 1 " q $end
$upscope $end
$scope module j3 $end
$var wire 1 ) clearb $end
$var wire 1 % clk $end
$var wire 1 + j $end
$var wire 1 + k $end
$var reg 1 ! q $end
$upscope $end
$upscope $end
$upscope $end
$enddefinitions $end
#0
$dumpvars
1-
1,
0+
0*
0)
0(
0'
0&
0%
0$
0#
0"
0!
$end
#5
1$
1&
1'
1(
1)
1%
#10
0%
#15
0$
1#
1%
#20
0%
#25
1*
1$
1%
#30
0%
#35
0*
0+
0$
0#
1"
1%
#40
0%
#45
1$
1%
#50
0%
#55
0$
1#
1%
#60
0%
#65
1+
1*
1$
1%
#70
0%
#75
0*
0+
0$
0#
0"
1!
1%
#80
0%
#85
1$
1%
#90
0%
#95
0$
1#
1%
#100
0%
#105
1*
1$
1%
#110
0%
#115
0*
0+
0$
0#
1"
1%
#120
0%
#125
1$
1%
#130
0%
#135
0$
1#
1%
#140
0%
#145
1+
1*
1$
1%
#150
0%
#155
0*
0+
0$
0#
0"
0!
1%
