Lab 3/Mealy Machine/q2.v
module ozooz (out, inp, clk, rst) ;
	output out ;
	input inp, clk, rst ;
	
	reg [2:0] state ;
	reg out ;
	
	//Uncomment line below if you want initial state to be pre-defined
	//initial begin state <= 3'b000 ; out = 1'b0 ; end
	
	always @(posedge clk or posedge rst)
	begin
		if (rst) begin
			state <= 3'b000 ;
			out <= 1'b0 ;
		end
		else begin
			case (state)
			3'b000 : begin
				if (inp) begin
					state <= 3'b001 ;
					out <= 1'b0 ;
				end
				else begin
					state <= 3'b000 ;
					out <= 1'b0 ;
				end
			end
			
			3'b001 : begin
				if (inp) begin
					state <= 3'b001 ;
					out <= 1'b0 ;
				end
				else begin
					state <= 3'b010 ;
					out <= 1'b0 ;
				end
			end
			
			3'b010 : begin
				if (inp) begin
					state <= 3'b011 ;
					out <= 1'b0 ;
				end
				else begin
					state <= 3'b000 ;
					out <= 1'b0 ;
				end
			end
			
			3'b011 : begin
				if (inp) begin
					state <= 3'b100 ;
					out <= 1'b0 ;
				end
				else begin
					state <= 3'b010 ;
					out <= 1'b0 ;
				end
			end
			
			3'b100 : begin
				if (inp) begin
					state <= 3'b001 ;
					out <= 1'b0 ;
				end
				else begin
					state <= 3'b010 ;
					out <= 1'b1 ;
				end
			end
			
			default: begin
				state <= 3'b000 ;
				out <= 0 ;
			end
			
			endcase
			
		end
	end
endmodule

Lab 3/Mealy Machine/q2_tb.v
`include "q2.v"

module testbench ;
	reg inp, clk, rst ;
	reg [10:0] seq ;
	wire out ;
	integer i ;
	
	ozooz mealy (out, inp, clk, rst) ;
	
	always #5 clk = ~clk ;
	
	initial begin
		$dumpfile ("q2_tb.vcd") ;
		$dumpvars (0 , testbench) ;
		clk = 0 ;
		rst = 0 ;
		seq = 11'b10110110101 ;
		
		//Resetting device
		#1 rst = 1 ;
		#2 rst = 0 ;
		
		#2 ;
		for (i = 0 ; i <= 10 ; i = i + 1)
		begin
			inp = seq[i] ;
			$display ("State = ", mealy.state, " Input = ", inp, " Output = ", out, "\n") ;
			
			if (i == 3) begin
				#6 rst = 0 ;
				#1 rst = 0 ;
				#3 ;
			end
			else	#10 ;
		end
		
		#0 $finish ;
	end
endmodule

Lab 3/Mealy Machine/q2_tb.vcd
$date
	Mon Oct 28 18:43:55 2019
$end
$version
	Icarus Verilog
$end
$timescale
	1s
$end
$scope module testbench $end
$var wire 1 ! out $end
$var reg 1 " clk $end
$var reg 1 # inp $end
$var reg 1 $ rst $end
$var reg 11 % seq [10:0] $end
$var integer 32 & i [31:0] $end
$scope module mealy $end
$var wire 1 " clk $end
$var wire 1 # inp $end
$var wire 1 $ rst $end
$var reg 1 ! out $end
$var reg 3 ' state [2:0] $end
$upscope $end
$upscope $end
$enddefinitions $end
#0
$dumpvars
b0 '
bx &
b10110110101 %
0$
x#
0"
0!
$end
#1
1$
#3
0$
#5
b1 '
1#
b0 &
1"
#10
0"
#15
b10 '
1"
0#
b1 &
#20
0"
#25
b11 '
1"
1#
b10 &
#30
0"
#35
b10 '
1"
0#
b11 &
#40
0"
#45
b11 '
1#
b100 &
1"
#50
0"
#55
b100 '
1"
b101 &
#60
0"
#65
1!
b10 '
1"
0#
b110 &
#70
0"
#75
0!
b11 '
1"
1#
b111 &
#80
0"
#85
b100 '
1"
b1000 &
#90
0"
#95
1!
b10 '
1"
0#
b1001 &
#100
0"
#105
0!
b11 '
1"
1#
b1010 &
#110
0"
#115
b100 '
1"
b1011 &
