Lab 3/DFF_ASYNC/dff_async.v
module dff_async (d, clearb, clock, q) ;
	input d, clearb, clock ;
	output q ;
	reg q ;
	
	always @(posedge clock or negedge clearb)
	begin
		if (!clearb) 
			q <= 1'b0 ;
		else
			q <= d ;
	end
endmodule

Lab 3/DFF_ASYNC/dff_async_tb.v
`include "dff_async.v"

module testbench ;
	reg d, clk, rst;
	wire q ;
	
	dff_async dff (d, rst, clk, q) ;

	always #5 clk = ~clk ;

	initial begin
		d = 0 ;
		clk = 0 ;
		rst = 1 ;
		$monitor($time , "d=%b, clk=%b, rst=%b, q=%b\n", d, clk, rst, q);
		$dumpfile ("dff_async.vcd") ;
		$dumpvars (0 , testbench) ;
		
		#5 d = 1'b1 ;
		#5 d = 1'b1 ;
		#5 d = 1'b0 ;
		#3 rst = 0 ;
		#5 d = 1'b1 ;
		#5 rst = 1 ;
		#3 rst = 0 ;
		#5 rst = 1 ;
		#3 rst = 0 ;
		#5 rst = 1 ;
		#3 rst = 0 ;
		#5 rst = 1 ;
		#2 d = 1'b1 ;
		#3 rst = 0 ;
		#5 rst = 1 ;
		#5 rst = 1 ;
		#2 d = 1'b0 ;
		#3 rst = 0 ;
		#3 rst = 0 ;
		#3 rst = 0 ;
		#5 rst = 1 ; 
		$finish ;
	end
endmodule

Lab 3/DFF_ASYNC/dff_async_tb.vcd
$date
	Wed Oct 16 09:16:42 2019
$end
$version
	Icarus Verilog
$end
$timescale
	1s
$end
$scope module testbench $end
$var wire 1 ! q $end
$var reg 1 " clk $end
$var reg 1 # d $end
$var reg 1 $ rst $end
$scope module dff $end
$var wire 1 $ clearb $end
$var wire 1 " clock $end
$var wire 1 # d $end
$var reg 1 ! q $end
$upscope $end
$upscope $end
$enddefinitions $end
#0
$dumpvars
1$
0#
0"
x!
$end
#5
1!
1#
1"
#10
0"
#15
0!
0#
1"
#18
0$
#20
0"
#23
1#
#25
1"
#28
1$
#30
0"
#31
0$
#35
1"
#36
1$
#39
0$
#40
0"
#44
1$
#45
1!
1"
#47
0!
0$
#50
0"
#52
1$
#55
1!
1"
#57
0!
0$
#60
0"
#62
1$
#65
1!
1"
#69
0#
#70
0"
#72
0!
0$
#75
1"
#80
0"
#83
1$
