Lab 3/JK_ASYNC/jk_async.v
module jk_async (j, k, clearb, clk, q) ;
	input j, k, clearb, clk ;
	output q ;
	reg q ;
	
	always @(posedge clk or negedge clearb)
	begin
		if (!clearb) 
			q <= 1'b0 ;
		else 
			if (j == 1'b0 && k == 1'b0) 
				q <= q ;
			else if (j == 1'b0 && k == 1'b1) 
				q <= 1'b0 ;
			else if (j == 1'b1 && k == 1'b0) 
				q <= 1'b1 ;
			else if (j == 1'b1 && k == 1'b1) 
				q <= ~q ;
	end
endmodule

Lab 3/JK_ASYNC/jk_async_tb.v
`include "jk_async.v"

module testbench ;
	reg j, k, rst, clk ;
	wire q ;
	
	jk_async jk(j, k, rst, clk, q) ;
	
	always #5 clk = ~clk;
	 
	initial begin
		j = 1 ;
		k = 1 ;
		rst = 1 ;
		clk = 0 ;
		$monitor ("rst = %b, clk = %b, j = %b, k = %b, q = %b\n" , rst, clk, j, k, q) ;
		$dumpfile ("jk_async.vcd") ;
		$dumpvars (0, testbench) ;
		
		#5 j = 1'b0 ; k = 1'b1 ;
		#10 j = 1'b0 ; k = 1'b0 ;
		#10 j = 1'b0 ; k = 1'b1 ;
		#10 j = 1'b1 ; k = 1'b0 ;
		#10 j = 1'b1 ; k = 1'b1 ;
		#3 //rst = 0 ;
		#5 //rst = 1 ;
		#3 //rst = 0 ;
		#5 //rst = 1 ;
		#3 j = 1'b1 ; k = 1'b0 ;
		#5 //rst = 1 ;
		#3 j = 1'b1 ; k = 1'b0 ;
		#5 //rst = 1 ;
		#2 j = 1'b1 ; k = 1'b1 ;
		#3 //rst = 0 ;
		#5 //rst = 1 ;
		#5 //rst = 1 ;
		#2 j = 1'b0 ; k = 1'b1 ;
		#3 //rst = 0 ;
		#3 //rst = 0 ;
		#3 j = 1'b1 ; k = 1'b0 ;
		#5 //rst = 1 ; 
		$finish ;
	end
endmodule

Lab 3/JK_ASYNC/jk_async.vcd
$date
	Mon Oct 28 13:13:10 2019
$end
$version
	Icarus Verilog
$end
$timescale
	1s
$end
$scope module testbench $end
$var wire 1 ! q $end
$var reg 1 " clk $end
$var reg 1 # j $end
$var reg 1 $ k $end
$var reg 1 % rst $end
$scope module jk $end
$var wire 1 % clearb $end
$var wire 1 " clk $end
$var wire 1 # j $end
$var wire 1 $ k $end
$var reg 1 ! q $end
$upscope $end
$upscope $end
$enddefinitions $end
#0
$dumpvars
1%
1$
1#
0"
x!
$end
#5
0!
0#
1"
#10
0"
#15
1"
0$
#20
0"
#25
1"
1$
#30
0"
#35
1!
1"
0$
1#
#40
0"
#45
0!
1"
1$
#50
0"
#55
1!
1"
#60
0"
#64
0$
#65
1"
#70
0"
#75
1"
#79
1$
#80
0"
#85
0!
1"
#90
0"
#94
0#
#95
1"
#100
0"
#103
0$
1#
#105
1!
1"
